fastcdc/.gitignore
fastcdc/__init__.py
fastcdc/benchmark.py
fastcdc/chunkify.py
fastcdc/cli.py
fastcdc/const.py
fastcdc/fastcdc_cy.pyx
fastcdc/fastcdc_py.py
fastcdc/original.py
fastcdc/scan.py
fastcdc/utils.py
fastcdc/fastcdc_cy.c
fastcdc/fastcdc_cy.cpython-312-darwin.so
fastcdc-1.7.0.dist-info/LICENSE
fastcdc-1.7.0.dist-info/METADATA
fastcdc-1.7.0.dist-info/WHEEL
fastcdc-1.7.0.dist-info/entry_points.txt
fastcdc-1.7.0.dist-info/RECORD
