Metadata-Version: 2.1
Name: fastcdc
Version: 1.7.0
Summary: FastCDC (content defined chunking) in pure Python.
Home-page: https://github.com/iscc/fastcdc-py
License: MIT
Keywords: cdc,chunking
Author: Titusz Pan
Author-email: tp@py7.de
Requires-Python: >=3.7.2,<4.0
Classifier: Environment :: Console
Classifier: Intended Audience :: Developers
Classifier: Intended Audience :: Information Technology
Classifier: License :: OSI Approved :: MIT License
Classifier: Operating System :: Microsoft :: Windows
Classifier: Operating System :: POSIX
Classifier: Operating System :: Unix
Classifier: Programming Language :: Python
Classifier: Programming Language :: Python :: 3
Classifier: Programming Language :: Python :: 3.8
Classifier: Programming Language :: Python :: 3.9
Classifier: Programming Language :: Python :: 3.10
Classifier: Programming Language :: Python :: 3.11
Classifier: Programming Language :: Python :: 3.6
Classifier: Programming Language :: Python :: 3.7
Classifier: Topic :: Multimedia
Classifier: Topic :: Software Development
Classifier: Topic :: System :: Archiving
Classifier: Topic :: Utilities
Provides-Extra: hashes
Requires-Dist: blake3 (>=0.3,<0.4) ; extra == "hashes"
Requires-Dist: click (>=8.1,<9.0)
Requires-Dist: click-default-group (>=1.2,<2.0)
Requires-Dist: codetiming (>=1.2,<2.0)
Requires-Dist: humanize (>=4.0,<5.0)
Requires-Dist: py-cpuinfo (>=9.0,<10.0)
Requires-Dist: xxhash (>=3.0,<4.0) ; extra == "hashes"
Project-URL: Repository, https://github.com/iscc/fastcdc-py
